LICENSE
README.md
setup.py
bin/run.py
cycling_stats.egg-info/PKG-INFO
cycling_stats.egg-info/SOURCES.txt
cycling_stats.egg-info/dependency_links.txt
cycling_stats.egg-info/not-zip-safe
cycling_stats.egg-info/requires.txt
cycling_stats.egg-info/top_level.txt
cyclingstats/__init__.py
cyclingstats/stats.py