Metadata-Version: 2.1
Name: cycling-stats
Version: 0.1.0
Summary: Calculate advanced cycling statistics from power and/or heart rate data
Home-page: https://github.com/evavanweenen/cycling-stats
Author: Eva van Weenen
Author-email: evanweenen@ethz.ch
License: MIT
License-File: LICENSE
